codeprompt/__init__.py
codeprompt/chatgpt_models.py
codeprompt/cli.py
codeprompt/codeprompt.py
codeprompt/promptstr.py
codeprompt/techniques/chunk.py
codeprompt/techniques/count_token.py
codeprompt/template.py
codeprompt-0.2.0.dist-info/entry_points.txt
codeprompt-0.2.0.dist-info/LICENSE
codeprompt-0.2.0.dist-info/METADATA
codeprompt-0.2.0.dist-info/WHEEL
codeprompt-0.2.0.dist-info/RECORD
