Metadata-Version: 2.1
Name: codeprompt
Version: 0.2.0
Summary: 
Author: Nutchanon Ninyawee
Author-email: nutchanon@codustry.com
Requires-Python: >=3.9,<4.0
Classifier: Programming Language :: Python :: 3
Classifier: Programming Language :: Python :: 3.9
Classifier: Programming Language :: Python :: 3.10
Classifier: Programming Language :: Python :: 3.11
Requires-Dist: click (>=8.1.3,<9.0.0)
Requires-Dist: jinja2 (>=3.1.2,<4.0.0)
Requires-Dist: loguru (>=0.7.0,<0.8.0)
Requires-Dist: pydantic (>=1.10.7,<2.0.0)
Requires-Dist: pygithub (>=1.58.1,<2.0.0)
Requires-Dist: pyperclip (>=1.8.2,<2.0.0)
Requires-Dist: python-frontmatter (>=1.0.0,<2.0.0)
Requires-Dist: tiktoken (>=0.3.3,<0.4.0)
